hoplite2/__init__.py
hoplite2/hoplite.py
hoplite2/layer_sparsity.py
hoplite2/spartan.py
hoplite2-0.3.0.dist-info/LICENSE
hoplite2-0.3.0.dist-info/WHEEL
hoplite2-0.3.0.dist-info/METADATA
hoplite2-0.3.0.dist-info/RECORD
