Metadata-Version: 2.1
Name: hoplite2
Version: 0.3.0
Summary: A Sparsity Analysis Tool and Library
Home-page: https://github.com/prydt/hoplite2
License: UNKNOWN
Author: Pranoy Dutta
Author-email: pranoydll@gmail.com
Classifier: License :: OSI Approved :: MIT License
Requires-Dist: Pillow >= 7.2.0
Requires-Dist: tensorflow >= 2.2.0
